tekoid/__init__.py
tekoid/base_client_sdk.py
tekoid/client.py
tekoid/code_client_sdk.py
tekoid/credentials_sdk.py
tekoid/errors.py
tekoid/utils.py
tekoid-3.0.2.dist-info/METADATA
tekoid-3.0.2.dist-info/WHEEL
tekoid-3.0.2.dist-info/top_level.txt
tekoid-3.0.2.dist-info/RECORD
