Metadata-Version: 2.1
Name: tekoid
Version: 3.0.2
Summary: UNKNOWN
Home-page: UNKNOWN
Author-email: viet.nk@teko.vn
License: UNKNOWN
Platform: UNKNOWN
Requires-Dist: requests
Requires-Dist: pyjwt
Requires-Dist: cryptography
